mathematical/__init__.py
mathematical/vec3.py
mathematicalpy-0.0.0.1.dist-info/LICENSE
mathematicalpy-0.0.0.1.dist-info/METADATA
mathematicalpy-0.0.0.1.dist-info/WHEEL
mathematicalpy-0.0.0.1.dist-info/entry_points.txt
mathematicalpy-0.0.0.1.dist-info/RECORD
