Metadata-Version: 2.1
Name: MathematicalPy
Version: 0.0.0.1
Summary: Mathematically-focused capabilities.
Home-page: https://github.com/dg-developer/MathematicalPy
License: Apache-2.0
Keywords: math,mathematical,simple,geometry,algebra,calculus,vector
Author: David Gayman
Author-email: drg.developer.2@gmail.com
Requires-Python: >=3.9,<4.0
Classifier: License :: OSI Approved :: Apache Software License
Classifier: Programming Language :: Python :: 3
Classifier: Programming Language :: Python :: 3.9
Classifier: Programming Language :: Python :: 3.10
Classifier: Programming Language :: Python :: 3.11
Classifier: Topic :: Scientific/Engineering :: Mathematics
Classifier: Topic :: Software Development :: Libraries
Requires-Dist: marvelouspy (>=0.0.0.3,<0.0.1.0)
Requires-Dist: numpy (>=1.25.2,<2.0.0)
Project-URL: Documentation, https://github.com/dg-developer/MathematicalPy
Project-URL: Repository, https://github.com/dg-developer/MathematicalPy
